README
setup.py
pyremotecv/__init__.py
pyremotecv/unique_queue.py
pyremotecv/utils.py
pyremotecv/version.py
pyremotecv.egg-info/PKG-INFO
pyremotecv.egg-info/SOURCES.txt
pyremotecv.egg-info/dependency_links.txt
pyremotecv.egg-info/requires.txt
pyremotecv.egg-info/top_level.txt