Metadata-Version: 1.0
Name: pyremotecv
Version: 0.5.0
Summary: pyremotecv is a client library for remotecv (https://github.com/globocom/remotecv/wiki).
Home-page: https://github.com/globocom/pyremotecv
Author: Time Home
Author-email: timehome@corp.globo.com
License: MIT
Keywords: facial feature detection opencv remote zeromq socket
Platform: UNKNOWN
Classifier: Development Status :: 3 - Alpha
Classifier: Intended Audience :: Developers
Classifier: License :: OSI Approved :: MIT License
Classifier: Natural Language :: English
Classifier: Operating System :: MacOS
Classifier: Operating System :: POSIX :: Linux
Classifier: Programming Language :: Python :: 2.6
